Metadata-Version: 2.2
Name: carecopy
Version: 1.0
Summary: carecopy: A simple file copy and comparison tool that allows to copy files and directories, compare files and directories, and estimate the time it will take to copy files.
Home-page: http://blog.cycleuser.org
Author: cycleuser
Author-email: cycleuser@cycleuser.org
License-File: LICENSE
Requires-Dist: pyside6
Dynamic: author
Dynamic: author-email
Dynamic: description
Dynamic: description-content-type
Dynamic: home-page
Dynamic: requires-dist
Dynamic: summary
